private_captcha/__init__.py
private_captcha/client.py
private_captcha/exceptions.py
private_captcha/models.py
private_captcha-0.0.6.dist-info/licenses/LICENSE
private_captcha-0.0.6.dist-info/METADATA
private_captcha-0.0.6.dist-info/WHEEL
private_captcha-0.0.6.dist-info/top_level.txt
private_captcha-0.0.6.dist-info/RECORD
