Metadata-Version: 2.4
Name: private-captcha
Version: 0.0.6
Summary: Python client library for Private Captcha API
Author-email: Taras Kushnir <hello@privatecaptcha.com>
License: MIT License
Project-URL: Homepage, https://docs.privatecaptcha.com/docs/integrations/python/
Project-URL: Repository, https://github.com/PrivateCaptcha/private-captcha-py
Classifier: Development Status :: 4 - Beta
Classifier: Intended Audience :: Developers
Classifier: License :: OSI Approved :: MIT License
Classifier: Programming Language :: Python :: 3
Classifier: Programming Language :: Python :: 3.8
Classifier: Programming Language :: Python :: 3.9
Classifier: Programming Language :: Python :: 3.10
Classifier: Programming Language :: Python :: 3.11
Classifier: Programming Language :: Python :: 3.12
Requires-Python: >=3.8
License-File: LICENSE
Provides-Extra: dev
Requires-Dist: coverage; extra == "dev"
Requires-Dist: pylint; extra == "dev"
Requires-Dist: black; extra == "dev"
Dynamic: license-file
